shex_to_shexj/__init__.py
shex_to_shexj/shex_to_shexj.py
shex_to_shexj-0.1.2.dist-info/AUTHORS
shex_to_shexj-0.1.2.dist-info/METADATA
shex_to_shexj-0.1.2.dist-info/WHEEL
shex_to_shexj-0.1.2.dist-info/entry_points.txt
shex_to_shexj-0.1.2.dist-info/pbr.json
shex_to_shexj-0.1.2.dist-info/top_level.txt
shex_to_shexj-0.1.2.dist-info/RECORD
