Metadata-Version: 2.1
Name: shex-to-shexj
Version: 0.1.2
Summary: ShExC to ShExJ conversion utility
Home-page: https://github.com/FHIRCat/shex_to_shexj/
Author: Harold Solbrig
Author-email: solbrig@jhu.edu
License: CC0 1.0 Universal
Keywords: fhir,shex,shexc,shexj
Platform: UNKNOWN
Classifier: Development Status :: 4 - Beta
Classifier: Environment :: Console
Classifier: Intended Audience :: Developers
Classifier: License :: CC0 1.0 Universal (CC0 1.0) Public Domain Dedication
Classifier: Programming Language :: Python :: 3 :: Only
Classifier: Programming Language :: Python :: 3.7
Classifier: Programming Language :: Python :: 3.8
Requires-Python: >=3.7
Requires-Dist: dirlistproc (>=1.4.5)
Requires-Dist: pyshex (>=0.7.14)
